[{"name":"sql.active_record","payload":{"sql":"              SELECT a.attname, format_type(a.atttypid, a.atttypmod),\n                     pg_get_expr(d.adbin, d.adrelid), a.attnotnull, a.atttypid, a.atttypmod\n                FROM pg_attribute a LEFT JOIN pg_attrdef d\n                  ON a.attrelid = d.adrelid AND a.attnum = d.adnum\n               WHERE a.attrelid = '\"trips\"'::regclass\n                 AND a.attnum \u003e 0 AND NOT a.attisdropped\n               ORDER BY a.attnum\n","name":"SCHEMA","connection_id":70257188606380,"statement_name":null,"binds":[],"line":36,"filename":"/Users/Chibird/Desktop/Projects/DayTrip/app/controllers/trips_controller.rb","method":"new"},"time":"2014-09-02T18:06:53.768-07:00","transaction_id":"6efa09af8bc13f168cfd","end":"2014-09-02T18:06:53.770-07:00","children":[],"duration":1.629},{"name":"sql.active_record","payload":{"sql":"              SELECT COUNT(*)\n              FROM pg_class c\n              LEFT JOIN pg_namespace n ON n.oid = c.relnamespace\n              WHERE c.relkind in ('v','r')\n              AND c.relname = 'trips'\n              AND n.nspname = ANY (current_schemas(false))\n","name":"SCHEMA","connection_id":70257188606380,"statement_name":null,"binds":[],"line":36,"filename":"/Users/Chibird/Desktop/Projects/DayTrip/app/controllers/trips_controller.rb","method":"new"},"time":"2014-09-02T18:06:53.773-07:00","transaction_id":"6efa09af8bc13f168cfd","end":"2014-09-02T18:06:53.774-07:00","children":[],"duration":0.758},{"name":"sql.active_record","payload":{"sql":"            SELECT attr.attname\n            FROM pg_attribute attr\n            INNER JOIN pg_constraint cons ON attr.attrelid = cons.conrelid AND attr.attnum = cons.conkey[1]\n            WHERE cons.contype = 'p'\n              AND cons.conrelid = '\"trips\"'::regclass\n","name":"SCHEMA","connection_id":70257188606380,"statement_name":null,"binds":[],"line":36,"filename":"/Users/Chibird/Desktop/Projects/DayTrip/app/controllers/trips_controller.rb","method":"new"},"time":"2014-09-02T18:06:53.775-07:00","transaction_id":"6efa09af8bc13f168cfd","end":"2014-09-02T18:06:53.775-07:00","children":[],"duration":0.635},{"name":"render_template.action_view","payload":{"identifier":"/Users/Chibird/Desktop/Projects/DayTrip/app/views/trips/new.html.erb","layout":"layouts/application"},"time":"2014-09-02T18:06:53.782-07:00","transaction_id":"6efa09af8bc13f168cfd","end":"2014-09-02T18:06:53.795-07:00","children":[],"duration":12.253},{"name":"process_action.action_controller","payload":{"controller":"TripsController","action":"new","params":{"action":"new","controller":"trips"},"format":"html","method":"GET","path":"/trips/new","status":200,"view_runtime":66.76899999999999,"db_runtime":2.946},"time":"2014-09-02T18:06:53.759-07:00","transaction_id":"6efa09af8bc13f168cfd","end":"2014-09-02T18:06:53.844-07:00","children":[],"duration":85.175}]